attend/__init__.py
attend/asym.py
attend/monarch.py
attend/ops.py
attend/sep.py
attend/sphere.py
attend-0.0.2.dist-info/METADATA
attend-0.0.2.dist-info/WHEEL
attend-0.0.2.dist-info/top_level.txt
attend-0.0.2.dist-info/RECORD
